{
  "symbol": "C",
  "timestamp": "2025-10-03T22:15:42Z",
  "data": {
    "spot": 97.34,
    "zero_gamma": 104.5,
    "net_gex": 556913,
    "call_gex": 36737687,
    "put_gex": -36180773,
    "call_walls": [
      100,
      105,
      97.5,
      99,
      102
    ],
    "put_walls": [
      95,
      96,
      90,
      97,
      92.5
    ],
    "call_walls_pct": [
      100.0,
      85.2,
      34.1,
      28.2,
      20.7
    ],
    "put_walls_pct": [
      100.0,
      35.3,
      29.9,
      20.8,
      7.6
    ],
    "total_call_oi": 75945,
    "total_put_oi": 69994,
    "total_oi": 145939,
    "put_call_oi_ratio": 0.92,
    "hvl": 95,
    "contracts": 93,
    "oi_vintage": "2025-10-03",
    "data_quality": "production",
    "source": "polygon"
  }
}