{
  "symbol": "CL",
  "timestamp": "2025-10-03T20:24:52Z",
  "data": {
    "spot": 78.31,
    "zero_gamma": 84.0,
    "net_gex": 367800,
    "call_gex": 907199,
    "put_gex": -539399,
    "call_walls": [
      85,
      83,
      80,
      82
    ],
    "put_walls": [
      78,
      74,
      70
    ],
    "call_walls_pct": [
      100.0,
      29.8,
      21.9,
      17.3
    ],
    "put_walls_pct": [
      100.0,
      45.1,
      7.0
    ],
    "total_call_oi": 3342,
    "total_put_oi": 832,
    "total_oi": 4174,
    "put_call_oi_ratio": 0.25,
    "hvl": 85,
    "contracts": 12,
    "oi_vintage": "2025-10-03",
    "data_quality": "production",
    "source": "polygon"
  }
}