{
  "symbol": "COP",
  "timestamp": "2025-10-03T15:26:07Z",
  "data": {
    "spot": 93.38,
    "zero_gamma": 97.75,
    "net_gex": 3023817,
    "call_gex": 9179416,
    "put_gex": -6155599,
    "call_walls": [
      100,
      95,
      97,
      97.5,
      98
    ],
    "put_walls": [
      91,
      93,
      90,
      92,
      92.5
    ],
    "call_walls_pct": [
      100.0,
      70.3,
      37.6,
      34.6,
      17.9
    ],
    "put_walls_pct": [
      100.0,
      68.5,
      46.1,
      35.4,
      31.4
    ],
    "total_call_oi": 18665,
    "total_put_oi": 11232,
    "total_oi": 29897,
    "put_call_oi_ratio": 0.6,
    "hvl": 100,
    "contracts": 38,
    "oi_vintage": "2025-10-03",
    "data_quality": "production",
    "source": "polygon"
  }
}