{
  "symbol": "GILD",
  "timestamp": "2025-10-03T23:31:52Z",
  "data": {
    "spot": 110.56,
    "zero_gamma": 114.5,
    "net_gex": 12219995,
    "call_gex": 19677401,
    "put_gex": -7457406,
    "call_walls": [
      118,
      115,
      120,
      114,
      113
    ],
    "put_walls": [
      110,
      105,
      108,
      100,
      109
    ],
    "call_walls_pct": [
      100.0,
      65.5,
      23.1,
      21.1,
      19.9
    ],
    "put_walls_pct": [
      100.0,
      16.3,
      5.5,
      4.6,
      4.5
    ],
    "total_call_oi": 36214,
    "total_put_oi": 14478,
    "total_oi": 50692,
    "put_call_oi_ratio": 0.4,
    "hvl": 118,
    "contracts": 32,
    "oi_vintage": "2025-10-03",
    "data_quality": "production",
    "source": "polygon"
  }
}