{
  "symbol": "JPM",
  "timestamp": "2025-10-03T23:13:09Z",
  "data": {
    "spot": 307.55,
    "zero_gamma": 313.75,
    "net_gex": 61196929,
    "call_gex": 130061210,
    "put_gex": -68864281,
    "call_walls": [
      315,
      320,
      310,
      330,
      335
    ],
    "put_walls": [
      300,
      290,
      305,
      295,
      307.5
    ],
    "call_walls_pct": [
      100.0,
      56.5,
      54.1,
      42.2,
      40.7
    ],
    "put_walls_pct": [
      100.0,
      15.0,
      13.1,
      7.8,
      7.8
    ],
    "total_call_oi": 73155,
    "total_put_oi": 45358,
    "total_oi": 118513,
    "put_call_oi_ratio": 0.62,
    "hvl": 300,
    "contracts": 87,
    "oi_vintage": "2025-10-03",
    "data_quality": "production",
    "source": "polygon"
  }
}