{
  "symbol": "LOW",
  "timestamp": "2025-10-03T21:22:45Z",
  "data": {
    "spot": 247.33,
    "zero_gamma": 258.75,
    "net_gex": 413473,
    "call_gex": 5365360,
    "put_gex": -4951887,
    "call_walls": [
      250,
      260,
      255,
      257.5
    ],
    "put_walls": [
      240,
      245
    ],
    "call_walls_pct": [
      100.0,
      82.4,
      26.2,
      13.2
    ],
    "put_walls_pct": [
      100.0,
      9.5
    ],
    "total_call_oi": 3399,
    "total_put_oi": 3015,
    "total_oi": 6414,
    "put_call_oi_ratio": 0.89,
    "hvl": 240,
    "contracts": 11,
    "oi_vintage": "2025-10-03",
    "data_quality": "production",
    "source": "polygon"
  }
}