{
  "symbol": "NFLX",
  "timestamp": "2025-10-03T19:26:26Z",
  "data": {
    "spot": 1162.53,
    "zero_gamma": 1162.53,
    "net_gex": -107366170,
    "call_gex": 231592682,
    "put_gex": -338958853,
    "call_walls": [
      1200,
      1220,
      1190,
      1250,
      1240
    ],
    "put_walls": [
      1150,
      1160,
      1140,
      1050,
      1130
    ],
    "call_walls_pct": [
      100.0,
      31.4,
      27.7,
      25.1,
      24.2
    ],
    "put_walls_pct": [
      100.0,
      69.2,
      66.5,
      64.4,
      62.2
    ],
    "total_call_oi": 39767,
    "total_put_oi": 62127,
    "total_oi": 101894,
    "put_call_oi_ratio": 1.56,
    "hvl": 1050,
    "contracts": 172,
    "oi_vintage": "2025-10-03",
    "data_quality": "production",
    "source": "polygon"
  }
}