{
  "symbol": "PEP",
  "timestamp": "2025-10-03T15:21:35Z",
  "data": {
    "spot": 142.31,
    "zero_gamma": 142.31,
    "net_gex": -35725823,
    "call_gex": 19755035,
    "put_gex": -55480859,
    "call_walls": [
      150,
      145,
      155,
      147,
      149
    ],
    "put_walls": [
      140,
      135,
      130,
      133,
      141
    ],
    "call_walls_pct": [
      100.0,
      94.8,
      42.5,
      25.8,
      20.3
    ],
    "put_walls_pct": [
      100.0,
      32.1,
      28.6,
      1.7,
      1.5
    ],
    "total_call_oi": 28919,
    "total_put_oi": 85878,
    "total_oi": 114797,
    "put_call_oi_ratio": 2.97,
    "hvl": 140,
    "contracts": 63,
    "oi_vintage": "2025-10-03",
    "data_quality": "production",
    "source": "polygon"
  }
}